akgpt/__init__.py
akgpt/main.py
akgpt-0.1.0.dist-info/licenses/LICENSE
akgpt-0.1.0.dist-info/METADATA
akgpt-0.1.0.dist-info/WHEEL
akgpt-0.1.0.dist-info/top_level.txt
akgpt-0.1.0.dist-info/RECORD
