Metadata-Version: 2.4
Name: akgpt
Version: 0.1.0
Summary: A Python library for interacting with Pollinations.ai API with support for text, images, and audio processing.
Author-email: Your Name <your.email@example.com>
Project-URL: Homepage, https://github.com/yourusername/akgpt
Project-URL: Bug Tracker, https://github.com/yourusername/akgpt/issues
Classifier: Programming Language :: Python :: 3
Classifier: License :: OSI Approved :: MIT License
Classifier: Operating System :: OS Independent
Requires-Python: >=3.8
License-File: LICENSE
Requires-Dist: requests
Dynamic: license-file
